dagster_shared/__init__.py
dagster_shared/error.py
dagster_shared/ipc.py
dagster_shared/match.py
dagster_shared/merger.py
dagster_shared/modules.py
dagster_shared/py.typed
dagster_shared/version.py
dagster_shared/check/README.md
dagster_shared/check/__init__.py
dagster_shared/check/builder.py
dagster_shared/check/decorator.py
dagster_shared/check/functions.py
dagster_shared/check/record.py
dagster_shared/cli/__init__.py
dagster_shared/dagster_model/__init__.py
dagster_shared/dagster_model/pydantic_compat_layer.py
dagster_shared/libraries/__init__.py
dagster_shared/plus/__init__.py
dagster_shared/plus/config.py
dagster_shared/plus/config_utils.py
dagster_shared/plus/login_server.py
dagster_shared/record/__init__.py
dagster_shared/scaffold/__init__.py
dagster_shared/serdes/__init__.py
dagster_shared/serdes/errors.py
dagster_shared/serdes/serdes.py
dagster_shared/serdes/utils.py
dagster_shared/serdes/objects/__init__.py
dagster_shared/serdes/objects/definition_metadata.py
dagster_shared/serdes/objects/package_entry.py
dagster_shared/serdes/objects/models/__init__.py
dagster_shared/serdes/objects/models/defs_state_info.py
dagster_shared/seven/__init__.py
dagster_shared/seven/abc.py
dagster_shared/seven/json.py
dagster_shared/seven/temp_dir.py
dagster_shared/seven/compat/__init__.py
dagster_shared/telemetry/__init__.py
dagster_shared/utils/__init__.py
dagster_shared/utils/cached_method.py
dagster_shared/utils/config.py
dagster_shared/utils/hash.py
dagster_shared/utils/test.py
dagster_shared/utils/timing.py
dagster_shared/utils/warnings.py
dagster_shared/yaml_utils/__init__.py
dagster_shared/yaml_utils/sample_yaml.py
dagster_shared/yaml_utils/source_position.py
dagster_shared-1.12.13.dist-info/licenses/LICENSE
dagster_shared-1.12.13.dist-info/METADATA
dagster_shared-1.12.13.dist-info/WHEEL
dagster_shared-1.12.13.dist-info/top_level.txt
dagster_shared-1.12.13.dist-info/RECORD
